odoo/addons/pos_lot_barcode/README.rst
odoo/addons/pos_lot_barcode/__init__.py
odoo/addons/pos_lot_barcode/__manifest__.py
odoo/addons/pos_lot_barcode/i18n/es.po
odoo/addons/pos_lot_barcode/i18n/fr.po
odoo/addons/pos_lot_barcode/i18n/it.po
odoo/addons/pos_lot_barcode/i18n/pos_lot_barcode.pot
odoo/addons/pos_lot_barcode/readme/CONFIGURATION.rst
odoo/addons/pos_lot_barcode/readme/CONTRIBUTORS.md
odoo/addons/pos_lot_barcode/readme/DESCRIPTION.md
odoo/addons/pos_lot_barcode/security/ir.model.access.csv
odoo/addons/pos_lot_barcode/static/description/icon.png
odoo/addons/pos_lot_barcode/static/description/index.html
odoo/addons/pos_lot_barcode/static/src/js/Popups/EditListPopup.esm.js
odoo/addons/pos_lot_barcode/static/src/js/Screens/ProductScreen.esm.js
odoo/addons/pos_lot_barcode/static/tests/tours/LotScanning.tour.esm.js
odoo/addons/pos_lot_barcode/tests/__init__.py
odoo/addons/pos_lot_barcode/tests/test_frontend.py
odoo_addon_pos_lot_barcode-18.0.1.0.0.3.dist-info/METADATA
odoo_addon_pos_lot_barcode-18.0.1.0.0.3.dist-info/WHEEL
odoo_addon_pos_lot_barcode-18.0.1.0.0.3.dist-info/top_level.txt
odoo_addon_pos_lot_barcode-18.0.1.0.0.3.dist-info/RECORD
